{
    "schema_version": 2,
    "timestamp": 1637741833,
    "workspace": {
        "0": [
            [
                {
                    "panes": [
                        {
                            "type": "term",
                            "directory": "/home/andrew",
                            "custom_colors": {
                                "fg_color": null,
                                "bg_color": null,
                                "palette": null
                            }
                        }
                    ],
                    "label": "fish /home/andrew",
                    "custom_label_set": false
                },
                {
                    "panes": [
                        {
                            "type": "term",
                            "directory": "/mnt/md126/conduit/frontend/src/frontend",
                            "custom_colors": {
                                "fg_color": null,
                                "bg_color": null,
                                "palette": null
                            }
                        }
                    ],
                    "label": "fish /mnt/md126/conduit/frontend/src/frontend",
                    "custom_label_set": false
                },
                {
                    "panes": [
                        {
                            "type": "term",
                            "directory": "/mnt/md126/conduit/frontend/src/frontend",
                            "custom_colors": {
                                "fg_color": null,
                                "bg_color": null,
                                "palette": null
                            }
                        }
                    ],
                    "label": "fish /mnt/md126/conduit/frontend/src/frontend",
                    "custom_label_set": false
                }
            ]
        ]
    }
}